fediverse/__init__.py
fediverse-0.0.0.dist-info/METADATA
fediverse-0.0.0.dist-info/WHEEL
fediverse-0.0.0.dist-info/licenses/LICENSE
fediverse-0.0.0.dist-info/RECORD
